flask_pydantic_docs/__init__.py
flask_pydantic_docs/openapi.py
flask_pydantic_docs/utils.py
flask_pydantic_docs/templates/redoc.html
flask_pydantic_docs/templates/swagger.html
Flask_Pydantic_Docs-0.0.17.dist-info/LICENSE
Flask_Pydantic_Docs-0.0.17.dist-info/METADATA
Flask_Pydantic_Docs-0.0.17.dist-info/WHEEL
Flask_Pydantic_Docs-0.0.17.dist-info/top_level.txt
Flask_Pydantic_Docs-0.0.17.dist-info/RECORD
