Metadata-Version: 2.1
Name: Flask-Pydantic-Docs
Version: 0.0.17
Summary: Add openapi docs to flask app using Flask-Pydantic
Home-page: https://github.com/buildpeak/flask_pydantic_docs
Author: Steve Guo
Author-email: buildpeak@gmail.com
License: UNKNOWN
Platform: UNKNOWN
License-File: LICENSE
Requires-Dist: Flask
Requires-Dist: pydantic
Requires-Dist: flask-pydantic
